yaast/__init__.py
yaast/__main__.py
yaast/awsconfigparser.py
yaast/write_session.py
yaast-0.1.5.data/scripts/console_url.sh
yaast-0.1.5.dist-info/LICENSE
yaast-0.1.5.dist-info/METADATA
yaast-0.1.5.dist-info/WHEEL
yaast-0.1.5.dist-info/entry_points.txt
yaast-0.1.5.dist-info/top_level.txt
yaast-0.1.5.dist-info/RECORD
