Metadata-Version: 2.1
Name: yaast
Version: 0.1.5
Summary: AWS credentials MFA-Resolver tool
Home-page: https://github.com/dynnamitt/yaast
Author: Kjetil Midtile
Author-email: kjetil.midtlie@gmail.com
Project-URL: Bug Tracker, https://github.com/dynnamitt/yaast
Classifier: Programming Language :: Python :: 3
Classifier: License :: OSI Approved :: MIT License
Classifier: Operating System :: OS Independent
Requires-Python: >=3.6
License-File: LICENSE
Requires-Dist: botocore
